persephonep
sample
