Metadata-Version: 1.0
Name: persephonep
Version: 2.0.1
Summary: Web Browser developed with Python3 and PyQt5
Home-page: https://github.com/montblanc18/persephonep
Author: Shin Kurita
Author-email: UNKNOWN
License: MIT
Platform: UNKNOWN
